{"nodes":[{"label":"Unity Health","x":-62.18934631347656,"y":174.65599060058594,"id":"36","attributes":{"researchunit":"TRUE","size":"1","Eccentricity":"2.0","Closeness Centrality":"0.5862068965517241","Degree":"5","researchunitname":"Applied Education Research Operatives (AERO) - St. Michael\u0027s","Betweenness Centrality":"0.08296568627450981","Harmonic Closeness Centrality":"0.6470588235294118","affiliationtype":"Fully Affiliated","Weighted Degree":"10.0","category":"Hospital","subcategory":"Hospital Network"},"color":"rgb(3,133,0)","size":5.0},{"label":"Wilson Centre","x":83.8983154296875,"y":57.09516525268555,"id":"5","attributes":{"researchunit":"N/A","size":"67","Eccentricity":"3.0","Closeness Centrality":"0.85","Degree":"15","researchunitname":"N/A","Betweenness Centrality":"0.5579656862745097","Harmonic Closeness Centrality":"0.9313725490196079","affiliationtype":"N/A","Weighted Degree":"70.0","category":"KMbO","subcategory":"KMbO"},"color":"rgb(0,199,255)","size":25.0},{"label":"CFD","x":178.7942657470703,"y":164.41897583007812,"id":"0","attributes":{"researchunit":"N/A","size":"20","Eccentricity":"3.0","Closeness Centrality":"0.5862068965517241","Degree":"6","researchunitname":"N/A","Betweenness Centrality":"0.035906862745098043","Harmonic Closeness Centrality":"0.6666666666666667","affiliationtype":"N/A","Weighted Degree":"17.0","category":"KMbO","subcategory":"KMbO"},"color":"rgb(0,199,255)","size":10.757575988769531},{"label":"Women\u0027s College Hospital","x":107.93253326416016,"y":-118.69902038574219,"id":"42","attributes":{"researchunit":"FALSE","size":"1","Eccentricity":"4.0","Closeness Centrality":"0.5","Degree":"3","researchunitname":"N/A","Betweenness Centrality":"0.0024509803921568627","Harmonic Closeness Centrality":"0.5637254901960784","affiliationtype":"Fully Affiliated","Weighted Degree":"5.0","category":"Hospital","subcategory":"Hospital"},"color":"rgb(140,185,0)","size":5.0},{"label":"CQUIPS","x":-45.354026794433594,"y":-43.92914962768555,"id":"3","attributes":{"researchunit":"N/A","size":"13","Eccentricity":"3.0","Closeness Centrality":"0.5666666666666667","Degree":"5","researchunitname":"N/A","Betweenness Centrality":"0.0303921568627451","Harmonic Closeness Centrality":"0.6372549019607844","affiliationtype":"N/A","Weighted Degree":"8.0","category":"KMbO","subcategory":"KMbO"},"color":"rgb(0,199,255)","size":8.636363983154297},{"label":"Trillium Health Partners","x":-417.2100524902344,"y":168.94215393066406,"id":"45","attributes":{"researchunit":"TRUE","size":"1","Eccentricity":"4.0","Closeness Centrality":"0.3148148148148148","Degree":"1","researchunitname":"N/A","Betweenness Centrality":"0.0","Harmonic Closeness Centrality":"0.3627450980392157","affiliationtype":"Associate Affiliated","Weighted Degree":"1.0","category":"Hospital","subcategory":"Hospital"},"color":"rgb(140,185,0)","size":5.0},{"label":"Sinai Health","x":73.34022521972656,"y":183.3333282470703,"id":"46","attributes":{"researchunit":"FALSE","size":"1","Eccentricity":"4.0","Closeness Centrality":"0.4857142857142857","Degree":"2","researchunitname":"N/A","Betweenness Centrality":"0.0","Harmonic Closeness Centrality":"0.5343137254901961","affiliationtype":"Fully Affiliated","Weighted Degree":"5.0","category":"Hospital","subcategory":"Hospital"},"color":"rgb(140,185,0)","size":5.0},{"label":"CPD","x":-1.3227208852767944,"y":218.92945861816406,"id":"2","attributes":{"researchunit":"N/A","size":"30","Eccentricity":"3.0","Closeness Centrality":"0.5862068965517241","Degree":"6","researchunitname":"N/A","Betweenness Centrality":"0.03590686274509804","Harmonic Closeness Centrality":"0.6666666666666667","affiliationtype":"N/A","Weighted Degree":"11.0","category":"KMbO","subcategory":"KMbO"},"color":"rgb(0,199,255)","size":13.78787899017334},{"label":"Baycrest","x":296.5209655761719,"y":267.3231506347656,"id":"39","attributes":{"researchunit":"FALSE","size":"1","Eccentricity":"4.0","Closeness Centrality":"0.4857142857142857","Degree":"2","researchunitname":"N/A","Betweenness Centrality":"0.0","Harmonic Closeness Centrality":"0.5343137254901961","affiliationtype":"Fully Affiliated","Weighted Degree":"2.0","category":"Hospital","subcategory":"Hospital"},"color":"rgb(140,185,0)","size":5.0},{"label":"Sunnybrook Health Sciences Centre","x":44.56959533691406,"y":-38.590797424316406,"id":"40","attributes":{"researchunit":"TRUE","size":"1","Eccentricity":"4.0","Closeness Centrality":"0.5","Degree":"3","researchunitname":"ERU","Betweenness Centrality":"0.0024509803921568627","Harmonic Closeness Centrality":"0.5637254901960784","affiliationtype":"Fully Affiliated","Weighted Degree":"13.0","category":"Hospital","subcategory":"Hospital"},"color":"rgb(140,185,0)","size":5.0},{"label":"Holland Bloorview Kids Rehabilitation Hospital","x":302.36932373046875,"y":-145.4149169921875,"id":"41","attributes":{"researchunit":"TRUE","size":"1","Eccentricity":"4.0","Closeness Centrality":"0.4857142857142857","Degree":"2","researchunitname":"Teaching \u0026 Learning Institute","Betweenness Centrality":"0.0","Harmonic Closeness Centrality":"0.5343137254901961","affiliationtype":"Fully Affiliated","Weighted Degree":"2.0","category":"Hospital","subcategory":"Hospital"},"color":"rgb(140,185,0)","size":5.0},{"label":"UHN","x":144.85015869140625,"y":63.35608673095703,"id":"38","attributes":{"researchunit":"TRUE","size":"1","Eccentricity":"4.0","Closeness Centrality":"0.5151515151515151","Degree":"4","researchunitname":"TIER; CEEP","Betweenness Centrality":"0.001838235294117647","Harmonic Closeness Centrality":"0.5931372549019608","affiliationtype":"Fully Affiliated","Weighted Degree":"39.0","category":"Hospital","subcategory":"Hospital Network"},"color":"rgb(3,133,0)","size":5.0},{"label":"Michael Garron Hospital","x":38.16020965576172,"y":-221.23057556152344,"id":"47","attributes":{"researchunit":"TRUE","size":"1","Eccentricity":"4.0","Closeness Centrality":"0.4722222222222222","Degree":"1","researchunitname":"N/A","Betweenness Centrality":"0.0","Harmonic Closeness Centrality":"0.5049019607843137","affiliationtype":"Associate Affiliated","Weighted Degree":"1.0","category":"Hospital","subcategory":"Hospital"},"color":"rgb(140,185,0)","size":5.0},{"label":"CIPE","x":250.17198181152344,"y":9.63520622253418,"id":"1","attributes":{"researchunit":"N/A","size":"14","Eccentricity":"3.0","Closeness Centrality":"0.6296296296296297","Degree":"8","researchunitname":"N/A","Betweenness Centrality":"0.06899509803921568","Harmonic Closeness Centrality":"0.7254901960784315","affiliationtype":"N/A","Weighted Degree":"15.0","category":"KMbO","subcategory":"KMbO"},"color":"rgb(0,199,255)","size":8.939393997192383},{"label":"T-CAIREM","x":-246.3607940673828,"y":155.6649932861328,"id":"4","attributes":{"researchunit":"N/A","size":"12","Eccentricity":"3.0","Closeness Centrality":"0.4473684210526316","Degree":"4","researchunitname":"N/A","Betweenness Centrality":"0.12622549019607843","Harmonic Closeness Centrality":"0.5392156862745098","affiliationtype":"N/A","Weighted Degree":"8.0","category":"KMbO","subcategory":"KMbO"},"color":"rgb(0,199,255)","size":8.333333969116211},{"label":"Hospital for Sick Children","x":-113.77848815917969,"y":87.5832290649414,"id":"43","attributes":{"researchunit":"TRUE","size":"1","Eccentricity":"2.0","Closeness Centrality":"0.5666666666666667","Degree":"4","researchunitname":"SickKids Learning Institute","Betweenness Centrality":"0.07083333333333335","Harmonic Closeness Centrality":"0.6176470588235294","affiliationtype":"Fully Affiliated","Weighted Degree":"12.0","category":"Hospital","subcategory":"Hospital"},"color":"rgb(140,185,0)","size":5.0},{"label":"North York General Hospital","x":-43.66171646118164,"y":-131.58274841308594,"id":"44","attributes":{"researchunit":"TRUE","size":"1","Eccentricity":"4.0","Closeness Centrality":"0.4857142857142857","Degree":"2","researchunitname":"N/A","Betweenness Centrality":"0.0","Harmonic Closeness Centrality":"0.5343137254901961","affiliationtype":"Associate Affiliated","Weighted Degree":"3.0","category":"Hospital","subcategory":"Hospital"},"color":"rgb(140,185,0)","size":5.0},{"label":"Centre for Addiction \u0026 Mental Health","x":87.1086654663086,"y":239.9751739501953,"id":"37","attributes":{"researchunit":"TRUE","size":"1","Eccentricity":"2.0","Closeness Centrality":"0.5483870967741935","Degree":"3","researchunitname":"Unnamed","Betweenness Centrality":"0.042892156862745105","Harmonic Closeness Centrality":"0.5882352941176471","affiliationtype":"Fully Affiliated","Weighted Degree":"6.0","category":"Hospital","subcategory":"Hospital"},"color":"rgb(140,185,0)","size":5.0}],"edges":[{"source":"1","target":"2","id":"12","attributes":{"participantid":"95","category":"KMbO/KMbO"},"color":"rgb(0,199,255)","size":1.0},{"source":"5","target":"43","id":"221","attributes":{"participantid":"139","category":"KMbO/Hospital"},"color":"rgb(70,192,127)","size":6.0},{"source":"0","target":"36","id":"164","attributes":{"participantid":"14","category":"KMbO/Hospital"},"color":"rgb(1,166,127)","size":2.0},{"source":"5","target":"39","id":"170","attributes":{"participantid":"12","category":"KMbO/Hospital"},"color":"rgb(70,192,127)","size":1.0},{"source":"2","target":"38","id":"217","attributes":{"participantid":"124","category":"KMbO/Hospital"},"color":"rgb(1,166,127)","size":3.0},{"source":"1","target":"40","id":"173","attributes":{"participantid":"19","category":"KMbO/Hospital"},"color":"rgb(70,192,127)","size":1.0},{"source":"5","target":"46","id":"205","attributes":{"participantid":"143","category":"KMbO/Hospital"},"color":"rgb(70,192,127)","size":4.0},{"source":"5","target":"41","id":"232","attributes":{"participantid":"110","category":"KMbO/Hospital"},"color":"rgb(70,192,127)","size":1.0},{"source":"1","target":"41","id":"177","attributes":{"participantid":"23","category":"KMbO/Hospital"},"color":"rgb(70,192,127)","size":1.0},{"source":"3","target":"44","id":"190","attributes":{"participantid":"37","category":"KMbO/Hospital"},"color":"rgb(70,192,127)","size":1.0},{"source":"4","target":"37","id":"195","attributes":{"participantid":"47","category":"KMbO/Hospital"},"color":"rgb(70,192,127)","size":1.0},{"source":"4","target":"36","id":"191","attributes":{"participantid":"50","category":"KMbO/Hospital"},"color":"rgb(1,166,127)","size":2.0},{"source":"0","target":"37","id":"166","attributes":{"participantid":"6","category":"KMbO/Hospital"},"color":"rgb(70,192,127)","size":2.0},{"source":"1","target":"36","id":"183","attributes":{"participantid":"30","category":"KMbO/Hospital"},"color":"rgb(1,166,127)","size":1.0},{"source":"1","target":"0","id":"4","attributes":{"participantid":"29","category":"KMbO/KMbO"},"color":"rgb(0,199,255)","size":1.0},{"source":"5","target":"2","id":"11","attributes":{"participantid":"124","category":"KMbO/KMbO"},"color":"rgb(0,199,255)","size":3.0},{"source":"0","target":"39","id":"169","attributes":{"participantid":"12","category":"KMbO/Hospital"},"color":"rgb(70,192,127)","size":1.0},{"source":"1","target":"38","id":"172","attributes":{"participantid":"95","category":"KMbO/Hospital"},"color":"rgb(1,166,127)","size":7.0},{"source":"5","target":"38","id":"182","attributes":{"participantid":"137","category":"KMbO/Hospital"},"color":"rgb(1,166,127)","size":25.0},{"source":"4","target":"43","id":"192","attributes":{"participantid":"49","category":"KMbO/Hospital"},"color":"rgb(70,192,127)","size":4.0},{"source":"2","target":"36","id":"199","attributes":{"participantid":"58","category":"KMbO/Hospital"},"color":"rgb(1,166,127)","size":2.0},{"source":"2","target":"43","id":"200","attributes":{"participantid":"56","category":"KMbO/Hospital"},"color":"rgb(70,192,127)","size":1.0},{"source":"5","target":"40","id":"208","attributes":{"participantid":"134","category":"KMbO/Hospital"},"color":"rgb(70,192,127)","size":8.0},{"source":"5","target":"47","id":"224","attributes":{"participantid":"102","category":"KMbO/Hospital"},"color":"rgb(70,192,127)","size":1.0},{"source":"1","target":"42","id":"179","attributes":{"participantid":"28","category":"KMbO/Hospital"},"color":"rgb(70,192,127)","size":1.0},{"source":"3","target":"40","id":"184","attributes":{"participantid":"36","category":"KMbO/Hospital"},"color":"rgb(70,192,127)","size":4.0},{"source":"5","target":"42","id":"214","attributes":{"participantid":"129","category":"KMbO/Hospital"},"color":"rgb(70,192,127)","size":3.0},{"source":"3","target":"42","id":"187","attributes":{"participantid":"34","category":"KMbO/Hospital"},"color":"rgb(70,192,127)","size":1.0},{"source":"5","target":"37","id":"218","attributes":{"participantid":"121","category":"KMbO/Hospital"},"color":"rgb(70,192,127)","size":3.0},{"source":"5","target":"44","id":"231","attributes":{"participantid":"130","category":"KMbO/Hospital"},"color":"rgb(70,192,127)","size":2.0},{"source":"3","target":"43","id":"186","attributes":{"participantid":"33","category":"KMbO/Hospital"},"color":"rgb(70,192,127)","size":1.0},{"source":"1","target":"5","id":"5","attributes":{"participantid":"95","category":"KMbO/KMbO"},"color":"rgb(0,199,255)","size":2.0},{"source":"0","target":"5","id":"0","attributes":{"participantid":"92","category":"KMbO/KMbO"},"color":"rgb(0,199,255)","size":7.0},{"source":"5","target":"3","id":"7","attributes":{"participantid":"86","category":"KMbO/KMbO"},"color":"rgb(0,199,255)","size":1.0},{"source":"4","target":"45","id":"194","attributes":{"participantid":"46","category":"KMbO/Hospital"},"color":"rgb(70,192,127)","size":1.0},{"source":"0","target":"38","id":"168","attributes":{"participantid":"92","category":"KMbO/Hospital"},"color":"rgb(1,166,127)","size":4.0},{"source":"5","target":"36","id":"165","attributes":{"participantid":"138","category":"KMbO/Hospital"},"color":"rgb(1,166,127)","size":3.0},{"source":"2","target":"46","id":"202","attributes":{"participantid":"61","category":"KMbO/Hospital"},"color":"rgb(70,192,127)","size":1.0}]}